openssm/Makefile
openssm/README.md
openssm/__init__.py
openssm/config.py
openssm/contrib/ssms/industrial_boilers_ssm/__init__.py
openssm/contrib/ssms/japan_fish_kcp_ssm/__init__.py
openssm/contrib/ssms/mri_operator_ssm/__init__.py
openssm/contrib/ssms/semiconductor_ssm/__init__.py
openssm/core/__init__.py
openssm/core/adapter/abstract_adapter.py
openssm/core/adapter/base_adapter.py
openssm/core/adapter/llama_index_adapter.py
openssm/core/backend/abstract_backend.py
openssm/core/backend/base_backend.py
openssm/core/backend/text_backend.py
openssm/core/inferencer/abstract_inferencer.py
openssm/core/inferencer/base_inferencer.py
openssm/core/slm/abstract_slm.py
openssm/core/slm/base_slm.py
openssm/core/slm/huggingface_slm.py
openssm/core/slm/memory/conversation_db.py
openssm/core/slm/memory/sqlite_conversation_db.py
openssm/core/slm/openai_slm.py
openssm/core/ssm/abstract_ssm.py
openssm/core/ssm/base_ssm.py
openssm/core/ssm/gpt3_llama_index_ssm.py
openssm/core/ssm/huggingface_ssm.py
openssm/core/ssm/openai_ssm.py
openssm/industrial/interpretability/README.md
openssm/industrial/monitoring/README.md
openssm/industrial/security/README.md
openssm/industrial/security/audit/README.md
openssm/industrial/security/best_practices/README.md
openssm/integration/README.md
openssm/integration/llamaindex/README.md
openssm/integration/testing_tools/README.md
openssm-0.1.3.dist-info/LICENSE.md
openssm-0.1.3.dist-info/METADATA
openssm-0.1.3.dist-info/WHEEL
openssm-0.1.3.dist-info/RECORD
