Metadata-Version: 2.1
Name: openssm
Version: 0.1.3
Summary: OpenSSM – 'Small Specialist Models' for Industrial AI
Author: Aitomatic Engineering
Author-email: engineering@aitomatic.com
Requires-Python: >=3.8.1,<4.0
Classifier: Programming Language :: Python :: 3
Classifier: Programming Language :: Python :: 3.9
Classifier: Programming Language :: Python :: 3.10
Classifier: Programming Language :: Python :: 3.11
Requires-Dist: accelerate (>=0.20.3,<0.21.0)
Requires-Dist: einops (>=0.6.1,<0.7.0)
Requires-Dist: llama-hub (>=0.0.4)
Requires-Dist: llama-index (>=0.6.33)
Requires-Dist: pypdf (>=3.11.0)
Requires-Dist: pytest (>=7.0.0)
Requires-Dist: torch (>=1.13.1)
Requires-Dist: transformers (>=4.30.2,<5.0.0)
